{
    "id": "lv081rm01",
    "parent": "lv080rm01",
    "name": "library-count-witness",
    "description": "The count stops at the door to the library as it closes, and then peeks into the windows of the door.\nThe Count then sees the girl being sucked into a book, and figures this must be what happened to the Princess.\nThe Count makes it back to Hubert and John.\n\nHit 1 if you wish to go to fairygodcollege-hubert-rescue.\n\nHit 0 to quit.",
    "doors": [
        {
            "id": "dr001",
            "choice": "1",
            "destination": "lv082rm01-fairygodcollege-hubert-rescue-plv081rm01"
        }
    ]
}